[
  {
    "scene": "Lightwave",
    "slot": "sceneTwo",
    "lights": [
      {
        "entity_id": "light.lamp",
        "rgb_color": [1,2,3],
        "brightness": 255
      }
    ]
  },
  {
    "scene": "Sea Breeze",
    "slot": "sceneThree"
  },
  {
    "scene": "Forest",
    "slot": "sceneFour"
  },
  {
    "scene": "Grass Barney",
    "slot": "diyMode"
  },
  {
    "scene": "Desert",
    "slot": "diyModeTwo"
  },
  {
    "scene": "Star Flow",
    "slot": "diyModeThree"
  },
  {
    "scene": "Grow",
    "slot": "segmented"
  },
  {
    "scene": "Green Fader",
    "slot": "segmentedTwo"
  },
  {
    "scene": "Dream Stars",
    "slot": "segmentedThree"
  },
  {
    "scene": "Cloud Dream",
    "slot": "segmentedFour"
  }
]
